{
  "$schema": "vscode://schemas/color-theme",
  "name": "Minimal Dark",
  "type": "dark",
  "colors": {
    "activityBar.activeBackground": "#1E1E1E",
    "activityBar.activeBorder": "#FFF",
    "activityBar.activeFocusBorder": "#BBBBBB",
    "activityBar.background": "#252526",
    "activityBar.border": "#252526",
    "activityBar.dropBorder": "#ffffff40",
    "activityBar.foreground": "#FFF",
    "activityBar.inactiveForeground": "#7c7c7d",

    "activityBarBadge.background": "#007ACC",
    "activityBarBadge.foreground": "#FFF",

    "badge.background": "#383B3D",
    "badge.foreground": "#DCDFE4",

    "breadcrumb.activeSelectionForeground": "#FFF",
    "breadcrumb.background": "#1E1E1E",
    "breadcrumb.focusForeground": "#ebebeb",
    "breadcrumb.foreground": "#BBBBBB",

    "breadcrumbPicker.background": "#252526",

    "button.background": "#383838",
    "button.foreground": "#FFF",
    "button.hoverBackground": "#ffffff28",

    "checkbox.background": "#383838",
    "checkbox.border": "#383838",
    "checkbox.foreground": "#DCDFE4",

    "contrastActiveBorder": "#00000000",

    "contrastBorder": "#00000000",

    "debugExceptionWidget.background": "#252526",

    "debugToolBar.background": "#252526",

    "dropdown.background": "#383838",
    "dropdown.border": "#383838",
    "dropdown.foreground": "#DCDFE4",
    "dropdown.listBackground": "#383838",

    "editor.background": "#1E1E1E",
    "editor.foreground": "#DCDFE4",
    "editor.inactiveSelectionBackground": "#103c57",
    "editor.selectionBackground": "#094f7e",
    "editor.selectionHighlightBackground": "#3A3D41",

    "editorGroup.border": "#252526",
    "editorGroup.dropBackground": "#ffffff16",

    "editorGroupHeader.noTabsBackground": "#ffffff16",
    "editorGroupHeader.tabsBackground": "#252526",

    "editorHoverWidget.background": "#252526",

    "editorIndentGuide.activeBackground1": "#707070",
    "editorIndentGuide.background1": "#404040",

    "editorLineNumber.foreground": "#707070",

    "editorSuggestWidget.background": "#252526",

    "editorWidget.background": "#252526",
    "editorWidget.border": "#383B3D",
    "editorWidget.foreground": "#DCDFE4",
    "editorWidget.resizeBorder": "#383B3D",

    "extensionButton.prominentBackground": "#0e639c",
    "extensionButton.prominentHoverBackground": "#1177bb",

    "focusBorder": "#383B3D",

    "foreground": "#DCDFE4",

    "icon.foreground": "#DCDFE4",

    "input.background": "#383838",
    "input.border": "#383B3D",
    "input.foreground": "#BBBBBB",
    "input.placeholderForeground": "#A6A6A6",

    "inputOption.activeBackground": "#00000000",
    "inputOption.activeBorder": "#00000000",
    "inputOption.activeForeground": "#FFF",

    "inputValidation.errorBackground": "#461410",
    "inputValidation.errorBorder": "#b00000",
    "inputValidation.errorForeground": "#DCDFE4",

    "list.activeSelectionBackground": "#e3f2ff22",
    "list.activeSelectionForeground": "#FFF",
    "list.dropBackground": "#383B3D",
    "list.focusBackground": "#ffffff14",
    "list.focusForeground": "#FFF",
    "list.hoverBackground": "#ffffff14",
    "list.hoverForeground": "#DCDFE4",
    "list.inactiveSelectionBackground": "#252526",

    "menu.background": "#252526",
    "menu.foreground": "#CCCCCC",
    "menu.selectionBackground": "#e3f2ff22",
    "menu.selectionForeground": "#ebebeb",
    "menu.separatorBackground": "#7c7c7d",

    "menubar.selectionBackground": "#e3f2ff22",
    "menubar.selectionForeground": "#ebebeb",

    "minimap.background": "#1E1E1E",

    "notificationCenterHeader.background": "#252526",

    "notifications.background": "#181818",

    "panel.background": "#1E1E1E",
    "panel.border": "#383838",
    "panel.dropBorder": "#ffffff40",

    "panelSection.dropBackground": "#ffffff16",

    "progressBar.background": "#007ACC",

    "sash.hoverBorder": "#383B3D",

    "scrollbar.shadow": "#00000060",

    "scrollbarSlider.activeBackground": "#e3f2ff44",
    "scrollbarSlider.background": "#e3f2ff22",
    "scrollbarSlider.hoverBackground": "#e3f2ff34",

    "settings.checkboxBackground": "#383838",
    "settings.checkboxBorder": "#383838",
    "settings.checkboxForeground": "#DCDFE4",
    "settings.dropdownBackground": "#383838",
    "settings.dropdownBorder": "#383838",
    "settings.dropdownForeground": "#DCDFE4",
    "settings.numberInputBackground": "#383838",
    "settings.textInputBackground": "#383838",

    "sideBar.background": "#1E1E1E",
    "sideBar.border": "#1E1E1E",
    "sideBar.dropBackground": "#ffffff16",
    "sideBar.foreground": "#BBBBBB",

    "sideBarSectionHeader.background": "#1E1E1E",
    "sideBarSectionHeader.border": "#1E1E1E",
    "sideBarSectionHeader.foreground": "#DCDFE4",

    "sideBarTitle.foreground": "#BBBBBB",

    "statusBar.background": "#252526",
    "statusBar.debuggingBackground": "#007ACC",
    "statusBar.foreground": "#FFF",
    "statusBar.noFolderBackground": "#252526",

    "statusBarItem.hoverBackground": "#e3f2ff22",
    "statusBarItem.remoteBackground": "#007ACC",
    "statusBarItem.remoteForeground": "#FFF",

    "tab.activeBackground": "#1E1E1E",
    "tab.activeBorder": "#1E1E1E",
    "tab.activeBorderTop": "#1E1E1E",
    "tab.activeForeground": "#FFF",
    "tab.border": "#1E1E1E",
    "tab.hoverBackground": "#1E1E1E",
    "tab.hoverBorder": "#1E1E1E",
    "tab.inactiveBackground": "#252526",
    "tab.inactiveForeground": "#BBBBBB",
    "tab.unfocusedHoverBackground": "#1E1E1E",
    "tab.unfocusedHoverBorder": "#1E1E1E",

    "terminal.ansiBlack": "#282C34",
    "terminal.ansiBlue": "#61AFEF",
    "terminal.ansiBrightBlack": "#5A6374",
    "terminal.ansiBrightBlue": "#61AFEF",
    "terminal.ansiBrightCyan": "#56B6C2",
    "terminal.ansiBrightGreen": "#98C379",
    "terminal.ansiBrightMagenta": "#C678DD",
    "terminal.ansiBrightRed": "#E06C75",
    "terminal.ansiBrightWhite": "#DCDFE4",
    "terminal.ansiBrightYellow": "#E5C07B",
    "terminal.ansiCyan": "#56B6C2",
    "terminal.ansiGreen": "#98C379",
    "terminal.ansiMagenta": "#C678DD",
    "terminal.ansiRed": "#E06C75",
    "terminal.ansiWhite": "#DCDFE4",
    "terminal.ansiYellow": "#E5C07B",

    "titleBar.activeBackground": "#252526",
    "titleBar.inactiveBackground": "#252526",
    "titleBar.inactiveForeground": "#7c7c7d",

    "welcomePage.background": "#1E1E1E",

    "widget.shadow": "#00000060"
  },
  "tokenColors": [
    {
      "name": "Comment",
      "scope": ["comment", "punctuation.definition.comment"],
      "settings": {
        "fontStyle": "italic",
        "foreground": "#546E7A"
      }
    }
  ]
}
